[
    {
        "District Name":"Congressional District 1",
        "Year":2022,
        "Congress":118,
        "Estimated Voting Age Population 30-44":"133714",
        "State":"45",
        "District Number":"01"
    },
    {
        "District Name":"Congressional District 2",
        "Year":2022,
        "Congress":118,
        "Estimated Voting Age Population 30-44":"132544",
        "State":"45",
        "District Number":"02"
    },
    {
        "District Name":"Congressional District 3",
        "Year":2022,
        "Congress":118,
        "Estimated Voting Age Population 30-44":"120531",
        "State":"45",
        "District Number":"03"
    },
    {
        "District Name":"Congressional District 4",
        "Year":2022,
        "Congress":118,
        "Estimated Voting Age Population 30-44":"130165",
        "State":"45",
        "District Number":"04"
    },
    {
        "District Name":"Congressional District 5",
        "Year":2022,
        "Congress":118,
        "Estimated Voting Age Population 30-44":"133335",
        "State":"45",
        "District Number":"05"
    },
    {
        "District Name":"Congressional District 6",
        "Year":2022,
        "Congress":118,
        "Estimated Voting Age Population 30-44":"134822",
        "State":"45",
        "District Number":"06"
    },
    {
        "District Name":"Congressional District 7",
        "Year":2022,
        "Congress":118,
        "Estimated Voting Age Population 30-44":"115845",
        "State":"45",
        "District Number":"07"
    }
]